odoo/addons/agreement_sale/README.rst
odoo/addons/agreement_sale/__init__.py
odoo/addons/agreement_sale/__manifest__.py
odoo/addons/agreement_sale/i18n/agreement_sale.pot
odoo/addons/agreement_sale/i18n/es.po
odoo/addons/agreement_sale/i18n/es_AR.po
odoo/addons/agreement_sale/i18n/it.po
odoo/addons/agreement_sale/i18n/sv.po
odoo/addons/agreement_sale/i18n/zh_CN.po
odoo/addons/agreement_sale/models/__init__.py
odoo/addons/agreement_sale/models/agreement.py
odoo/addons/agreement_sale/models/res_config_settings.py
odoo/addons/agreement_sale/models/sale.py
odoo/addons/agreement_sale/readme/CONTRIBUTORS.md
odoo/addons/agreement_sale/readme/DESCRIPTION.md
odoo/addons/agreement_sale/readme/ROADMAP.md
odoo/addons/agreement_sale/security/ir.model.access.csv
odoo/addons/agreement_sale/static/description/icon.png
odoo/addons/agreement_sale/static/description/index.html
odoo/addons/agreement_sale/views/agreement_menu.xml
odoo/addons/agreement_sale/views/agreement_view.xml
odoo/addons/agreement_sale/views/res_config_settings.xml
odoo/addons/agreement_sale/views/sale_order.xml
odoo_addon_agreement_sale-18.0.1.0.3.1.dist-info/METADATA
odoo_addon_agreement_sale-18.0.1.0.3.1.dist-info/WHEEL
odoo_addon_agreement_sale-18.0.1.0.3.1.dist-info/top_level.txt
odoo_addon_agreement_sale-18.0.1.0.3.1.dist-info/RECORD
